ultimate_hosts_blacklist/whitelist/__init__.py
ultimate_hosts_blacklist/whitelist/configuration.py
ultimate_hosts_blacklist/whitelist/core.py
ultimate_hosts_blacklist/whitelist/parser.py
ultimate_hosts_blacklist/whitelist/rzdb.py
ultimate_hosts_blacklist_whitelist_dev-3.27.4.dist-info/LICENSE
ultimate_hosts_blacklist_whitelist_dev-3.27.4.dist-info/METADATA
ultimate_hosts_blacklist_whitelist_dev-3.27.4.dist-info/WHEEL
ultimate_hosts_blacklist_whitelist_dev-3.27.4.dist-info/entry_points.txt
ultimate_hosts_blacklist_whitelist_dev-3.27.4.dist-info/top_level.txt
ultimate_hosts_blacklist_whitelist_dev-3.27.4.dist-info/RECORD
