Metadata-Version: 2.1
Name: ultimate-hosts-blacklist-whitelist-dev
Version: 3.27.4
Summary: The whitelisting tool of the Ultimate Hosts Blacklist project.
Home-page: https://github.com/Ultimate-Hosts-Blacklist/whitelist/tree/script
Author: funilrys
Author-email: contact@funilrys.com
License: MIT
Keywords: Python,hosts,hosts file,whitelist
Platform: any
Classifier: Environment :: Console
Classifier: Topic :: Internet
Classifier: Development Status :: 5 - Production/Stable
Classifier: Intended Audience :: Developers
Classifier: Programming Language :: Python
Classifier: Programming Language :: Python :: 3
Classifier: License :: OSI Approved :: MIT License
License-File: LICENSE
Requires-Dist: colorama
Requires-Dist: domain2idna
Requires-Dist: pyfunceble-dev>=4.2.26
Requires-Dist: requests
Requires-Dist: ultimate-hosts-blacklist-helpers>=1.5.2
Requires-Dist: urllib3
